anysynth/__init__.py
anysynth/_version.py
anysynth-0.0.1.dist-info/METADATA
anysynth-0.0.1.dist-info/WHEEL
anysynth-0.0.1.dist-info/licenses/LICENSE
anysynth-0.0.1.dist-info/RECORD
